tool.py
ja_testlib-1.0.0.dist-info/DESCRIPTION.rst
ja_testlib-1.0.0.dist-info/METADATA
ja_testlib-1.0.0.dist-info/RECORD
ja_testlib-1.0.0.dist-info/WHEEL
ja_testlib-1.0.0.dist-info/metadata.json
ja_testlib-1.0.0.dist-info/top_level.txt
testlib/__init__.py
testlib/testlibone.py
